d_ff_mtcmos.v
module d_ff_mtcmos(
    input D, clk, rst, sleep,
    output Q
);
    reg state;  // Internal state register

    always @(posedge clk or posedge rst)
    begin 
        if (rst)
            state <= 1'b0; // Reset the state
        else if (!sleep)
            state <= D; // Update the state if not in sleep mode
    end

    // Continuous assignment for Q
    assign Q = (sleep) ? 1'b0 : state;
endmodule

d_ff_mtcmos_tb.v
module d_ff_mtcmos_tb;
    reg D, clk, rst, sleep;
    wire Q;

    // Instantiate the d_ff_mtcmos module
    d_ff_mtcmos uut (
        .D(D),
        .clk(clk),
        .rst(rst),
        .sleep(sleep),
        .Q(Q)
    );

    // Clock generation
    initial begin
        clk = 0;
        forever #10 clk = ~clk;  // Toggle clock every 5 time units
    end

    // Test sequence
    initial begin
        // Initialize signals
        rst = 0;D = 1;sleep = 0;#10;
        // Apply reset
        rst = 1;D = 0;#10;
        // Test normal operation
        rst = 0;D = 0;#10;
        D = 1;#10;
        // Test sleep mode
        sleep = 1;#10;
        sleep = 0;#10;
    end

    // Stop simulation after 1000 time units
    initial begin
        #1000 $finish;
    end

    // Dump waveforms for debugging
    initial begin
        $dumpfile("dump.vcd");
        $dumpvars(1, d_ff_mtcmos_tb);  // Use 1 instead of 0 to limit scope
    end
endmodule

dump.vcd
$date
	Thu Mar 20 14:46:28 2025
$end
$version
	Icarus Verilog
$end
$timescale
	1s
$end
$scope module d_ff_mtcmos_tb $end
$var wire 1 ! Q $end
$var reg 1 " D $end
$var reg 1 # clk $end
$var reg 1 $ rst $end
$var reg 1 % sleep $end
$upscope $end
$enddefinitions $end
#0
$dumpvars
0%
0$
0#
1"
x!
$end
#5
1!
1#
#10
0!
0#
0"
1$
#15
1#
#20
0#
0$
#25
1#
#30
0#
1"
#35
1!
1#
#40
0!
0#
1%
#45
1#
#50
1!
0#
0%
